brms/__init__.py
brms/main.py
brms/accounting/__init__.py
brms/accounting/account.py
brms/accounting/journal.py
brms/accounting/ledger.py
brms/accounting/report.py
brms/accounting/statement_viewer.py
brms/controllers/__init__.py
brms/controllers/bank_book_controller.py
brms/controllers/bank_controller.py
brms/controllers/base.py
brms/controllers/inspector_controller.py
brms/controllers/main_controller.py
brms/controllers/yield_curve_controller.py
brms/data/__init__.py
brms/data/data_loader.py
brms/data/schema.py
brms/data/default/__init__.py
brms/instruments/__init__.py
brms/instruments/amortizing_fixed_rate_loan.py
brms/instruments/base.py
brms/instruments/cash.py
brms/instruments/commitment.py
brms/instruments/common_equity.py
brms/instruments/covered_bond.py
brms/instruments/credit_card.py
brms/instruments/deposit.py
brms/instruments/factory.py
brms/instruments/fixed_rate_bond.py
brms/instruments/letter_of_credit.py
brms/instruments/mock.py
brms/instruments/mortgage.py
brms/instruments/personal_loan.py
brms/instruments/registry.py
brms/instruments/repurchase_agreement.py
brms/instruments/treasury_security.py
brms/instruments/visitors/__init__.py
brms/instruments/visitors/base.py
brms/instruments/visitors/inspection.py
brms/instruments/visitors/valuation.py
brms/metrics/__init__.py
brms/metrics/base.py
brms/metrics/credit_risk/__init__.py
brms/metrics/credit_risk/central_counterparties_default_approach.py
brms/metrics/credit_risk/counterparty_risk_default_approach.py
brms/metrics/credit_risk/fall_back_approach.py
brms/metrics/credit_risk/internal_assessment_approach.py
brms/metrics/credit_risk/internal_ratings_based_approach.py
brms/metrics/credit_risk/look_through_approach.py
brms/metrics/credit_risk/mandate_based_approach.py
brms/metrics/credit_risk/rwa.py
brms/metrics/credit_risk/secrutisation_internal_ratings_based_approach.py
brms/metrics/credit_risk/securitisation_external_ratings_based_approach.py
brms-0.1.0.dev2.dist-info/LICENSE
brms-0.1.0.dev2.dist-info/METADATA
brms-0.1.0.dev2.dist-info/WHEEL
brms-0.1.0.dev2.dist-info/entry_points.txt
brms-0.1.0.dev2.dist-info/top_level.txt
brms-0.1.0.dev2.dist-info/RECORD
