Metadata-Version: 2.2
Name: brms
Version: 0.1.0.dev2
Summary: A bank risk management simulation framework.
Author-email: Mingze Gao <adrian.gao@outlook.com>
Project-URL: Homepage, https://bankrisk.org
Classifier: Programming Language :: Python :: 3
Classifier: License :: OSI Approved :: MIT License
Classifier: Operating System :: OS Independent
Requires-Python: >=3.11
License-File: LICENSE
Requires-Dist: matplotlib>=3.10.0
Requires-Dist: pandas>=2.2.3
Requires-Dist: pyside6==6.8.1
Requires-Dist: qtawesome>=1.3.1
Requires-Dist: quantlib>=1.36
Requires-Dist: rich>=13.9.4
Requires-Dist: tabulate>=0.9.0
